evla_mcast/__init__.py
evla_mcast/angles.py
evla_mcast/controller.py
evla_mcast/mcast_clients.py
evla_mcast/scan_config.py
evla_mcast/xsd/widarCommon.xsd
evla_mcast/xsd/observe/AntennaPropertyTable.xsd
evla_mcast/xsd/observe/Eop.xsd
evla_mcast/xsd/observe/Observation.xsd
evla_mcast/xsd/observe/Tcal.xsd
evla_mcast/xsd/vci/vciCommon.xsd
evla_mcast/xsd/vci/vciLog.xsd
evla_mcast/xsd/vci/vciRequest.xsd
evla_mcast/xsd/vci/vciResponse.xsd
evla_mcast/xsd/vci/vciStbBbSlopeTable.xsd
evla_mcast/xsd/vci/vciStbDelayModel.xsd
evla_mcast/xsd/vci/vciStbSwitchedPowerTable.xsd
evla_mcast-0.2.1.dist-info/DESCRIPTION.rst
evla_mcast-0.2.1.dist-info/METADATA
evla_mcast-0.2.1.dist-info/RECORD
evla_mcast-0.2.1.dist-info/WHEEL
evla_mcast-0.2.1.dist-info/metadata.json
evla_mcast-0.2.1.dist-info/top_level.txt
