Metadata-Version: 2.0
Name: evla-mcast
Version: 0.2.1
Summary: Receive and handle EVLA multicast messages
Home-page: https://github.com/demorest/evla_mcast/
Author: Paul Demorest
Author-email: pdemores@nrao.edu
License: UNKNOWN
Platform: UNKNOWN
Classifier: Programming Language :: Python
Classifier: Programming Language :: Python :: 2.7
Classifier: Programming Language :: Python :: 3.6
Requires-Dist: future
Requires-Dist: lxml
